{"disruptions":[{"id":"1d3edd9a-270e-11f0-8e2e-0a58a9feac02","applicationPeriods":[{"begin":"20250502T062200","end":"20250502T100000"}],"lastUpdate":"20250502T063002","cause":"PERTURBATION","severity":"BLOQUANTE","title":"Tramway T4 - Défaut d'alimentation électrique  : Trafic interrompu entre République Marx Dormoy et Hôpital entre 06h et 10h.","message":"<p>Le trafic est interrompu entre les stations République Marx Dormoy &nbsp;et Hôpital de la ligne T4 entre 06h et 10h.<br><br>Motif : &nbsp;Défaut d'alimentation électrique&nbsp;<\/p>","disruption_id":"1d3ecbac-270e-11f0-8e2e-0a58a9feac02"},{"id":"74cfb94c-271a-11f0-8e2e-0a58a9feac02","applicationPeriods":[{"begin":"20250502T063853","end":"20250502T075424"}],"lastUpdate":"20250502T075823","cause":"PERTURBATION","severity":"BLOQUANTE","tags":["Actualité"],"title":"Ligne J : Paris St-Lazare <-> Ermont - Eaubonne trafic perturbé","message":"<p>Le trafic est perturb&#233; entre Paris Saint-Lazare et Ermont - Eaubonne dans les 2 sens. <br><br>Pour plus d'informations sur cette perturbation, consultez le <a href=\"https:\/\/twitter.com\/LIGNEJ_SNCF\">fil Twitter de la ligne J<\/a>. <br><br>Motif : Incident affectant la voie dans le secteur d'Ermont-Eaubonne.<br><\/p>","shortMessage":"interruption","disruption_id":"f1b3a61c-2710-11f0-8e2e-0a58a9feac02"},{"id":"769e6002-0591-11f0-9201-0a58a9feac02","applicationPeriods":[{"begin":"20250502T030000","end":"20250503T030000"}],"lastUpdate":"20250320T144436","cause":"TRAVAUX","severity":"PERTURBEE","tags":["Actualité"],"title":"Ligne P : Paris Est - Château-Thierry 7\/04 - 2\/05","message":"<p class=\"Paragraph SCXO135967776 BCX0\" xml:lang=\"FR-FR\" lang=\"FR-FR\"><\/p><p>P&#233;riode : toute la journ&#233;e \n<br>\n<br>Dates : du lundi 7 avril au vendredi 2 mai, en semaine.\n<br>\n<br>L'horaire de certains trains entre Paris Est et Ch&#226;teau-Thierry est avanc&#233; ou retard&#233;. \n<br>\n<br>Les horaires du calculateur d'itin&#233;raire tiennent compte des travaux. \n<br>\n<br>Motif : travaux (limitation temporaire de la vitesse des trains). <\/p><br><p><\/p>","shortMessage":"trafic ralenti","disruption_id":"769b844a-0591-11f0-9201-0a58a9feac02"},{"id":"46a11f9a-0675-11f0-9201-0a58a9feac02","applicationPeriods":[{"begin":"20250321T120000","end":"20251103T030000"}],"lastUpdate":"20250321T175740","cause":"TRAVAUX","severity":"PERTURBEE","title":"Tramway T2 : Travaux de modernisation - Trafic interrompu","message":"<p>Jusqu'au 2 novembre, le trafic est interrompu entre Porte de Versailles et Suzanne Lenglen en raison de travaux de modernisation.<br>Pour rejoindre la Porte de Versailles, depuis Suzanne Lenglen, rejoindre à pied la station Balard du T3<\/p>","disruption_id":"46a03ca6-0675-11f0-9201-0a58a9feac02"},{"id":"6bd130e6-10c7-11f0-8f48-0a58a9feac02","applicationPeriods":[{"begin":"20250502T090000","end":"20250502T160000"}],"lastUpdate":"20250403T220834","cause":"TRAVAUX","severity":"PERTURBEE","tags":["Actualité"],"title":"RER D Goussainville Melun 06 mars au 22 août 2025","message":"<p>P&#233;riode : du lundi au vendredi sauf jours f&#233;ri&#233;s, de 09h00 &#224; 16h00.<br><br>Dates : du 03\/02\/2025 au 22\/08\/2025<br><\/p><p>Un train sur deux circule au d&#233;part ou est limit&#233; &#224; Combs La Ville. <br><br>Les horaires du calculateur d'itin&#233;raire tiennent compte des travaux.<br><br><br>Motif : travaux sur les voies de garage &#224; Melun.<br><br><br><\/p>","shortMessage":"trafic ralenti","disruption_id":"6bb024d2-10c7-11f0-8f48-0a58a9feac02"},{"id":"b3d3d1c0-18ef-11f0-8f48-0a58a9feac02","applicationPeriods":[{"begin":"20250502T090000","end":"20250502T160000"}],"lastUpdate":"20250414T071704","cause":"TRAVAUX","severity":"PERTURBEE","tags":["Actualité"],"title":"RER D Goussainville Melun 06 mars au 22 août 2025","message":"<p>P&#233;riode : de 09h00 &#224; 16h00.<br><br>Dates : du lundi 31 mars au vendredi 2 mai sauf week-end et jours f&#233;ri&#233;s. <br><\/p><p>Un train sur deux circule au d&#233;part ou est limit&#233; &#224; Combs La Ville. <br><br>Les horaires du calculateur d'itin&#233;raire tiennent compte des travaux.<br><br><br>Motif : travaux sur les voies de garage &#224; Melun.<br><br><br><\/p>","shortMessage":"trafic ralenti","disruption_id":"b3b723e0-18ef-11f0-8f48-0a58a9feac02"},{"id":"fdcf8210-18ef-11f0-8f48-0a58a9feac02","applicationPeriods":[{"begin":"20250502T090000","end":"20250502T160000"}],"lastUpdate":"20250414T071908","cause":"TRAVAUX","severity":"PERTURBEE","tags":["Actualité"],"title":"RER D Goussainville Melun 06 mars au 22 août 2025","message":"<p>P&#233;riode : de 09h00 &#224; 16h00.<br><br>Dates : du lundi 31 mars au vendredi 2 mai sauf week-end et jours f&#233;ri&#233;s. <br><\/p><p>Un train sur deux circule au d&#233;part ou est limit&#233; &#224; Combs La Ville. <br><br>Les horaires du calculateur d'itin&#233;raire tiennent compte des travaux.<br><br><br>Motif : travaux sur les voies de garage &#224; Melun.<br><br><br><\/p>","shortMessage":"trafic ralenti","disruption_id":"fdbd9348-18ef-11f0-8f48-0a58a9feac02"},{"id":"6c9372ea-1f55-11f0-9e35-0a58a9feac02","applicationPeriods":[{"begin":"20250502T090000","end":"20250502T160000"}],"lastUpdate":"20250422T104020","cause":"TRAVAUX","severity":"PERTURBEE","tags":["Actualité"],"title":"RER D Goussainville Melun 31\/03 au 02\/05","message":"<p>P&#233;riode : de 09h00 &#224; 16h00.<br><br>Dates : du lundi 31 mars au vendredi 2 mai sauf week-end et jours f&#233;ri&#233;s. <br><\/p><p>Un train sur deux circule au d&#233;part ou est limit&#233; &#224; Combs La Ville. <br><br>Les horaires du calculateur d'itin&#233;raire tiennent compte des travaux.<br><br><br>Motif : travaux sur les voies de garage &#224; Melun.<br><br><br><\/p>","shortMessage":"trafic ralenti","disruption_id":"6c687338-1f55-11f0-9e35-0a58a9feac02"},{"id":"e686f2c0-21a8-11f0-9e35-0a58a9feac02","applicationPeriods":[{"begin":"20250425T030000","end":"20250503T030000"}],"lastUpdate":"20250425T094255","cause":"PERTURBATION","severity":"PERTURBEE","tags":["Actualité"],"title":"ligne B : adaptation offre de transport du 1er au 2 mai.","message":"<p>P&#233;riode: 01\/05 au 02\/05<br><\/p><p>Pendant le pont, le 1er et 2 mai, les horaires changent. Pr&#233;parez votre trajet sur ces dates en consultant le site ou appli ile de France Mobilit&#233;s, les sites Transilien.com et Ratp.fr, SNCF Connect ou votre application de mobilit&#233;. Retrouvez les horaires sur le site du RERB : maligneb.fr <\/p><br><p><\/p>","shortMessage":"trafic ralenti","disruption_id":"e6869334-21a8-11f0-9e35-0a58a9feac02"},{"id":"caf1941c-23b9-11f0-b11a-0a58a9feac02","applicationPeriods":[{"begin":"20250502T090000","end":"20250502T160000"}],"lastUpdate":"20250428T004853","cause":"TRAVAUX","severity":"PERTURBEE","tags":["Actualité"],"title":"RER D Goussainville Melun 31\/03 au 02\/05","message":"<p>P&#233;riode : de 09h00 &#224; 16h00.<br><br>Dates : du lundi 31 mars au vendredi 2 mai sauf week-end et jours f&#233;ri&#233;s. <br><\/p><p>Un train sur deux circule au d&#233;part ou est limit&#233; &#224; Combs La Ville. <br><br>Les horaires du calculateur d'itin&#233;raire tiennent compte des travaux.<br><br><br>Motif : travaux sur les voies de garage &#224; Melun.<br><br><br><\/p>","shortMessage":"trafic ralenti","disruption_id":"caaf070a-23b9-11f0-b11a-0a58a9feac02"},{"id":"95c082d4-24b9-11f0-9be1-0a58a9feac02","applicationPeriods":[{"begin":"20250502T090000","end":"20250502T160000"}],"lastUpdate":"20250429T071954","cause":"TRAVAUX","severity":"PERTURBEE","tags":["Actualité"],"title":"RER D Goussainville Melun 31\/03 au 02\/05","message":"<p>P&#233;riode : de 09h00 &#224; 16h00.<br><br>Dates : du lundi 31 mars au vendredi 2 mai sauf week-end et jours f&#233;ri&#233;s. <br><\/p><p><br><\/p><p>Un train sur deux circulent entre les gares de Melun et Combs la Ville.<br><br>Les horaires du calculateur d'itin&#233;raire tiennent compte des travaux.<br><br><br>Motif : travaux sur les voies de garage &#224; Melun.<br><br><br><\/p>","shortMessage":"trafic ralenti","disruption_id":"955d0128-24b9-11f0-9be1-0a58a9feac02"},{"id":"97825f10-24ba-11f0-a1ce-0a58a9feac02","applicationPeriods":[{"begin":"20250502T090000","end":"20250502T160000"}],"lastUpdate":"20250429T072707","cause":"TRAVAUX","severity":"PERTURBEE","tags":["Actualité"],"title":"RER D Goussainville Melun 31\/03 au 02\/05","message":"<p>P&#233;riode : de 09h00 &#224; 16h00.<br><br>Dates : du lundi 28 avril au vendredi 30 mai sauf week-end et jours f&#233;ri&#233;s. <br><\/p><p><br><\/p><p>Un train sur deux circulent entre les gares de Melun et Combs la Ville.<br><br>Les horaires du calculateur d'itin&#233;raire tiennent compte des travaux.<br><br><br>Motif : travaux sur les voies de garage &#224; Melun.<br><br><br><\/p>","shortMessage":"trafic ralenti","disruption_id":"9772c3a2-24ba-11f0-a1ce-0a58a9feac02"},{"id":"27c29f1a-24c3-11f0-8217-0a58a9feac02","applicationPeriods":[{"begin":"20250429T030000","end":"20250503T030000"}],"lastUpdate":"20250429T082825","cause":"PERTURBATION","severity":"PERTURBEE","tags":["Actualité"],"title":"Ligne D : adaptation de l’offre de transport","message":"<p>Les vendredis 2, 9 et 30 Mai, l&#8217;offre de transport sera adapt&#233;e sur votre ligne. Certains trains ne circuleront pas.<\/p><p><br>Pour pr&#233;parer votre trajet et avant de vous rendre en gare, v&#233;rifiez vos horaires sur l&#8217;appli Ile-de-France Mobilit&#233;s, le site Transilien.com, SNCF Connect ou votre appli de mobilit&#233;<\/p><p><\/p>","shortMessage":"trafic ralenti","disruption_id":"27c23de0-24c3-11f0-8217-0a58a9feac02"},{"id":"20bb09f6-2567-11f0-9be1-0a58a9feac02","applicationPeriods":[{"begin":"20250430T030000","end":"20250505T030000"}],"lastUpdate":"20250430T040211","cause":"PERTURBATION","severity":"PERTURBEE","tags":["Actualité"],"title":"RER C : Issy non desservie en direction de Versailles ","message":"<p><\/p><p>P&#233;riode : &#224; partir du lundi 05 mai<br>Gare : Issy<br><br>- Arr&#234;t non desservi sens Paris -&gt; Versailles<br>- Arr&#234;t desservi sens Versailles -&gt; Paris<br><br>La gare d'Issy sera de nouveau desservie &#224; partir du lundi 05 mai, seulement dans le sens de Versailles vers Paris pour raison de s&#233;curit&#233;.<br><br>Motif : mesure de s&#233;curit&#233;.<\/p>","shortMessage":"Arrêt non desservi planifié","disruption_id":"20b8607a-2567-11f0-9be1-0a58a9feac02"},{"id":"c3b37bc8-2596-11f0-8217-0a58a9feac02","applicationPeriods":[{"begin":"20250502T030000","end":"20250503T030000"}],"lastUpdate":"20250430T094311","cause":"TRAVAUX","severity":"PERTURBEE","tags":["Actualité"],"title":"ligne J : Paris St-Lazare - Poissy du 01 au 04\/05","message":"<p><\/p><p><\/p><p>P&#233;riode : toute la journ&#233;e.<\/p><p>Dates : du jeudi 1er au dimanche 04 mai.<br><\/p><p>Le trafic est interrompu entre Paris Saint-Lazare &lt;&gt; Poissy.<br><br>Jeudi 1er, samedi 03 et dimanche 04 mai :<br>- Renforcement des lignes de bus r&#233;guli&#232;res, l&#8217;Express A14 entre La D&#233;fense &lt;&gt; Les Mureaux et La D&#233;fense &lt;&gt; Mantes la Jolie.<br>- Renforcement de lignes r&#233;guli&#232;res bus 01 entre Poissy &lt;&gt; Saint-Germain en Laye.<br><br>Vendredi 02 mai jusqu&#8217;&#224; 22h00 :<br>- Pour rejoindre les gares de Poissy &#224; Mantes la Jolie, nous vous conseillons d&#8217;emprunter le RER A jusqu&#8217;&#224; Poissy puis la ligne J direction Mantes la jolie.<br><br>Les horaires du calculateur d'itin&#233;raire tiennent compte des travaux.\u000b\u000b<\/p><p>Motif : travaux.<br><\/p><p><br><\/p><br><br><br><p><\/p>","shortMessage":"Trafic interrompu planifié","disruption_id":"a940e3d4-0f07-11f0-bb7e-0a58a9feac02"},{"id":"865b00b4-25fc-11f0-9be1-0a58a9feac02","applicationPeriods":[{"begin":"20250409T030000","end":"20250505T030000"}],"lastUpdate":"20250430T215136","cause":"PERTURBATION","severity":"PERTURBEE","tags":["Actualité"],"title":"RER C : Issy non desservie","message":"<p><\/p><p><\/p><p><\/p><p>P&#233;riode : Tous les jours jusqu'&#224; nouvel avis.<br><br>Suite aux travaux, la gare d'Issy n'est plus desservie pour raison de s&#233;curit&#233; jusqu'au dimanche 04 mai inclus.<br><br>A partir du lundi 05 mai, la gare d'Issy sera de nouveau accessible, seulement dans le sens Versailles vers Paris.<br><br>Motif : mesures de s&#233;curit&#233;.<\/p><p><\/p>","shortMessage":"Arrêt non desservi planifié","disruption_id":"7022fcc4-1540-11f0-8f48-0a58a9feac02"},{"id":"0901dbbc-261d-11f0-8217-0a58a9feac02","applicationPeriods":[{"begin":"20250502T030000","end":"20250503T030000"}],"lastUpdate":"20250501T014419","cause":"TRAVAUX","severity":"PERTURBEE","tags":["Actualité"],"title":"RER C : Champ de Mars - Pontoise du 01 au 04\/05 et du 08 au 11\/05","message":"<p><\/p><p>P&#233;riode : Tout le week-end.<br>Dates : jeudis 1er et 08, vendredis 02 et 09, samedis 03 et 10 et dimanches 04 et 11 mai.<br><br>Aucun train ne circule entre Champ de Mars - Montigny Beauchamp et Pontoise.<br><br>Report : Lignes du M&#233;tro, Tramway et lignes de bus de ville.<br><\/p><p>Motif : Travaux.<br><\/p><p><\/p>","shortMessage":"Trafic interrompu planifié","disruption_id":"06199c42-0cae-11f0-b7af-0a58a9feac02"},{"id":"cfe27566-2717-11f0-976f-0a58a9feac02","applicationPeriods":[{"begin":"20250502T060000","end":"20250502T100000"}],"lastUpdate":"20250502T073927","cause":"TRAVAUX","severity":"PERTURBEE","tags":["Actualité"],"title":"Entre Montargis et Paris Lyon : Modification de composition","message":"<p>Les trains suivants voit leurs compositions r&#233;duit :<\/p><p>- POMA d&#233;part Montargis &#224; 08h10, arriv&#233;e Paris Lyon &#224; 09h51<\/p><p>Retrouvez tous les horaires de vos trains dans la rubrique itin&#233;raires ou prochains d&#233;part.&nbsp;<\/p>","shortMessage":"trafic ralenti","disruption_id":"fab69294-2709-11f0-ab49-0a58a9feac02"},{"id":"cc09385c-2718-11f0-ab49-0a58a9feac02","applicationPeriods":[{"begin":"20250502T074000","end":"20250502T085000"}],"lastUpdate":"20250502T074630","cause":"TRAVAUX","severity":"PERTURBEE","tags":["Actualité"],"title":"Entre Paris Lyon et Montereau : modification de composition ","message":"<p><\/p><p>Les trains suivants voit leurs compositions r&#233;duit :<\/p>\n<br>- KUMO d&#233;part Paris Lyon &#224; 07h46, arriv&#233;e Montereau &#224; 08h44.<p><\/p><p>\n- PUMA d&#233;part Montereau &#224; 09h15, arriv&#233;e Paris Lyon &#224; 10h13.<\/p><p><br>Retrouvez tous les horaires de vos trains dans la rubrique itin&#233;raires ou prochains d&#233;part. <\/p><p><\/p>","shortMessage":"trafic ralenti","disruption_id":"5d8ed5da-2718-11f0-8e2e-0a58a9feac02"},{"id":"74e90f6e-271a-11f0-8e2e-0a58a9feac02","applicationPeriods":[{"begin":"20250502T075350","end":"20250502T090000"}],"lastUpdate":"20250502T075823","cause":"PERTURBATION","severity":"PERTURBEE","tags":["Actualité"],"title":"Ligne J : Paris St-Lazare <-> Ermont - Eaubonne trafic perturbé","message":"<p>Le trafic est perturb&#233; entre Paris Saint-Lazare et Ermont - Eaubonne dans les 2 sens. <br><br>Pour plus d'informations sur cette perturbation, consultez le <a href=\"https:\/\/twitter.com\/LIGNEJ_SNCF\">fil Twitter de la ligne J<\/a>. <br><br>Motif : Incident affectant la voie dans le secteur d'Ermont-Eaubonne.<br><\/p>","shortMessage":"trafic ralenti","disruption_id":"f1b3a61c-2710-11f0-8e2e-0a58a9feac02"},{"id":"3e06b4aa-271b-11f0-8e2e-0a58a9feac02","applicationPeriods":[{"begin":"20250502T080100","end":"20250502T085000"}],"lastUpdate":"20250502T080400","cause":"PERTURBATION","severity":"PERTURBEE","tags":["Actualité"],"title":"Ligne T12 : suppressions","message":"<p><\/p><p>Les trams suivants sont supprim&#233;s :<br><br>- au d&#233;part de Massy Palaiseau 7h59 en direction d'Evry Courcouronnes,<br><br>-  au d&#233;part d'Evry Courcouronnes 7h34 en direction de Massy Palaiseau,<\/p><p><\/p><p>- au d&#233;part d'Evry Courcouronnes 8h49 en direction de Massy Palaiseau.<\/p><br><br>Motif : panne d'un tramway &#224; Epinay sur Orge.<br><p><\/p><p><\/p>","shortMessage":"trafic ralenti","disruption_id":"3e066252-271b-11f0-8e2e-0a58a9feac02"},{"id":"4f75bf56-271b-11f0-ab49-0a58a9feac02","applicationPeriods":[{"begin":"20250502T080200","end":"20250503T043000"}],"lastUpdate":"20250502T080430","cause":"PERTURBATION","severity":"PERTURBEE","tags":["Actualité"],"title":"Métro 5 : Incident technique sur un train - Trafic perturbé","message":"<p>Le trafic est perturbé sur toute la ligne en raison d'un incident technique sur un train à Eglise de Pantin.<br><a href='http:\/\/www.ratp.fr'>Plus d'informations sur le site ratp.fr<\/a><\/p>","shortMessage":"Trafic perturbé","disruption_id":"01482366-2714-11f0-8e2e-0a58a9feac02"},{"id":"7ce66e0e-271b-11f0-ab49-0a58a9feac02","applicationPeriods":[{"begin":"20250502T075904","end":"20250502T093000"}],"lastUpdate":"20250502T080546","cause":"PERTURBATION","severity":"PERTURBEE","tags":["Actualité"],"title":"RER D : Corbeil-Essonnes -> Villeneuve St-G trafic ralenti","message":"<p>Le trafic est ralenti de Corbeil-Essonnes vers Villeneuve S Georges. <br><\/p><p>Des allongements de temps de trajet jusqu'&#224;10 minutes, des modifications de desserte et des suppressions sont &#224; pr&#233;voir.<\/p><p>Pour plus d'informations sur cette perturbation, consultez le <a href=\"https:\/\/twitter.com\/RERD_SNCF\">fil Twitter du RER D<\/a>. <br><br>Motif : panne d'un train dans le secteur de Bras de Fer (incident termin&#233;).<br><\/p>","shortMessage":"trafic ralenti","disruption_id":"d9aede6a-271a-11f0-976f-0a58a9feac02"},{"id":"6a80bafc-1f6f-11f0-ab2b-0a58a9feac02","applicationPeriods":[{"begin":"20250418T104300","end":"20250511T223000"}],"lastUpdate":"20250422T134624","cause":"PERTURBATION","severity":"INFORMATION","tags":["Actualité"],"title":"Ligne J : Argenteuil forte affluence","message":"<p>P&#233;riode : de 10h &#224; 22h<br><br>Dates : du 18 avril au 11 mai 2025<br>&nbsp;<br>Risque de forte affluence en gare et &#224; bord des trains au d&#233;part et &#224; l'arriv&#233;e de Argenteuil.<br><\/p><p>Les derniers trains au d&#233;part de Argenteuil vers Paris Saint Lazare sont :<\/p><p>* en semaine : 00h05, 00h19, 00h35, 00h49<\/p><p>* le samedi : 23h49, 00h04, 00h19, 00h37<\/p><p>* le dimanche : 23h35, 23h40, 23h49, 00h54<br><\/p><p><\/p><p>Ces horaires sont susceptibles d&#8217;&#233;voluer en cas de travaux. <br><\/p><p>Pour pr&#233;parer votre trajet, consultez l'appli Ile-de-France Mobilit&#233;s, le site de <a href=\"https:\/\/www.transilien.com\/fr\/itineraire\">Transilien.com<\/a>, <a href=\"https:\/\/www.sncf-connect.com\/\">SNCF Connect<\/a> ou votre appli de mobilit&#233;.<\/p><p><br><\/p>Motif : &#233;v&#232;nement sur la commune d'Argenteuil<br><p><\/p>","shortMessage":"forte affluence","disruption_id":"7927a3e4-1c32-11f0-b0e8-0a58a9feac02"}],"lines":[{"id":"line:IDFM:C01375","name":"5","shortName":"5","mode":"Metro","networkId":"network:IDFM:Operator_100","impactedObjects":[{"type":"line","id":"line:IDFM:C01375","name":"5","disruptionIds":["4f75bf56-271b-11f0-ab49-0a58a9feac02"]}]},{"id":"line:IDFM:C01376","name":"6","shortName":"6","mode":"Metro","networkId":"network:IDFM:Operator_100","impactedObjects":[]},{"id":"line:IDFM:C01379","name":"9","shortName":"9","mode":"Metro","networkId":"network:IDFM:Operator_100","impactedObjects":[]},{"id":"line:IDFM:C01380","name":"10","shortName":"10","mode":"Metro","networkId":"network:IDFM:Operator_100","impactedObjects":[]},{"id":"line:IDFM:C01383","name":"13","shortName":"13","mode":"Metro","networkId":"network:IDFM:Operator_100","impactedObjects":[]},{"id":"line:IDFM:C01384","name":"14","shortName":"14","mode":"Metro","networkId":"network:IDFM:Operator_100","impactedObjects":[]},{"id":"line:IDFM:C01390","name":"T2","shortName":"T2","mode":"Tramway","networkId":"network:IDFM:Operator_100","impactedObjects":[{"type":"line","id":"line:IDFM:C01390","name":"T2","disruptionIds":["46a11f9a-0675-11f0-9201-0a58a9feac02"]}]},{"id":"line:IDFM:C01742","name":"A","shortName":"A","mode":"RapidTransit","networkId":"network:IDFM:71","impactedObjects":[]},{"id":"line:IDFM:C01743","name":"B","shortName":"B","mode":"RapidTransit","networkId":"network:IDFM:71","impactedObjects":[{"type":"line","id":"line:IDFM:C01743","name":"B","disruptionIds":["e686f2c0-21a8-11f0-9e35-0a58a9feac02"]}]},{"id":"line:IDFM:C01727","name":"C","shortName":"C","mode":"RapidTransit","networkId":"network:IDFM:71","impactedObjects":[{"type":"line","id":"line:IDFM:C01727","name":"C","disruptionIds":["0901dbbc-261d-11f0-8217-0a58a9feac02","20bb09f6-2567-11f0-9be1-0a58a9feac02","865b00b4-25fc-11f0-9be1-0a58a9feac02"]},{"type":"stop_point","id":"stop_point:IDFM:monomodalStopPlace:462357","name":"Issy - Val de Seine","disruptionIds":["20bb09f6-2567-11f0-9be1-0a58a9feac02","865b00b4-25fc-11f0-9be1-0a58a9feac02"]},{"type":"stop_point","id":"stop_point:IDFM:monomodalStopPlace:43163","name":"Meudon Val Fleury","disruptionIds":["20bb09f6-2567-11f0-9be1-0a58a9feac02","865b00b4-25fc-11f0-9be1-0a58a9feac02"]},{"type":"stop_point","id":"stop_point:IDFM:monomodalStopPlace:43084","name":"Issy","disruptionIds":["20bb09f6-2567-11f0-9be1-0a58a9feac02","865b00b4-25fc-11f0-9be1-0a58a9feac02"]}]},{"id":"line:IDFM:C01728","name":"D","shortName":"D","mode":"RapidTransit","networkId":"network:IDFM:71","impactedObjects":[{"type":"line","id":"line:IDFM:C01728","name":"D","disruptionIds":["27c29f1a-24c3-11f0-8217-0a58a9feac02","6bd130e6-10c7-11f0-8f48-0a58a9feac02","6c9372ea-1f55-11f0-9e35-0a58a9feac02","95c082d4-24b9-11f0-9be1-0a58a9feac02","97825f10-24ba-11f0-a1ce-0a58a9feac02","b3d3d1c0-18ef-11f0-8f48-0a58a9feac02","caf1941c-23b9-11f0-b11a-0a58a9feac02","fdcf8210-18ef-11f0-8f48-0a58a9feac02","7ce66e0e-271b-11f0-ab49-0a58a9feac02"]},{"type":"stop_point","id":"stop_point:IDFM:monomodalStopPlace:470195","name":"Gare de Lyon","disruptionIds":["6bd130e6-10c7-11f0-8f48-0a58a9feac02","6c9372ea-1f55-11f0-9e35-0a58a9feac02","b3d3d1c0-18ef-11f0-8f48-0a58a9feac02","caf1941c-23b9-11f0-b11a-0a58a9feac02","fdcf8210-18ef-11f0-8f48-0a58a9feac02"]},{"type":"stop_point","id":"stop_point:IDFM:monomodalStopPlace:45739","name":"Juvisy","disruptionIds":["7ce66e0e-271b-11f0-ab49-0a58a9feac02"]},{"type":"stop_point","id":"stop_point:IDFM:monomodalStopPlace:45735","name":"Vigneux-sur-Seine","disruptionIds":["7ce66e0e-271b-11f0-ab49-0a58a9feac02"]},{"type":"stop_point","id":"stop_point:IDFM:monomodalStopPlace:43115","name":"Corbeil-Essonnes","disruptionIds":["7ce66e0e-271b-11f0-ab49-0a58a9feac02"]},{"type":"stop_point","id":"stop_point:IDFM:monomodalStopPlace:43225","name":"Viry-Châtillon","disruptionIds":["7ce66e0e-271b-11f0-ab49-0a58a9feac02"]},{"type":"stop_point","id":"stop_point:IDFM:monomodalStopPlace:43154","name":"Maisons-Alfort - Alfortville","disruptionIds":["6bd130e6-10c7-11f0-8f48-0a58a9feac02","6c9372ea-1f55-11f0-9e35-0a58a9feac02","b3d3d1c0-18ef-11f0-8f48-0a58a9feac02","caf1941c-23b9-11f0-b11a-0a58a9feac02","fdcf8210-18ef-11f0-8f48-0a58a9feac02"]},{"type":"stop_point","id":"stop_point:IDFM:monomodalStopPlace:464040","name":"Le Vert de Maisons","disruptionIds":["6bd130e6-10c7-11f0-8f48-0a58a9feac02","6c9372ea-1f55-11f0-9e35-0a58a9feac02","b3d3d1c0-18ef-11f0-8f48-0a58a9feac02","caf1941c-23b9-11f0-b11a-0a58a9feac02","fdcf8210-18ef-11f0-8f48-0a58a9feac02"]},{"type":"stop_point","id":"stop_point:IDFM:monomodalStopPlace:45067","name":"Villeneuve-Saint-Georges","disruptionIds":["6bd130e6-10c7-11f0-8f48-0a58a9feac02","6c9372ea-1f55-11f0-9e35-0a58a9feac02","b3d3d1c0-18ef-11f0-8f48-0a58a9feac02","caf1941c-23b9-11f0-b11a-0a58a9feac02","fdcf8210-18ef-11f0-8f48-0a58a9feac02","7ce66e0e-271b-11f0-ab49-0a58a9feac02"]},{"type":"stop_point","id":"stop_point:IDFM:monomodalStopPlace:43204","name":"Stade de France Saint-Denis","disruptionIds":["6bd130e6-10c7-11f0-8f48-0a58a9feac02","6c9372ea-1f55-11f0-9e35-0a58a9feac02","b3d3d1c0-18ef-11f0-8f48-0a58a9feac02","caf1941c-23b9-11f0-b11a-0a58a9feac02","fdcf8210-18ef-11f0-8f48-0a58a9feac02"]},{"type":"stop_point","id":"stop_point:IDFM:monomodalStopPlace:46286","name":"Créteil Pompadour","disruptionIds":["6bd130e6-10c7-11f0-8f48-0a58a9feac02","6c9372ea-1f55-11f0-9e35-0a58a9feac02","b3d3d1c0-18ef-11f0-8f48-0a58a9feac02","caf1941c-23b9-11f0-b11a-0a58a9feac02","fdcf8210-18ef-11f0-8f48-0a58a9feac02"]},{"type":"stop_point","id":"stop_point:IDFM:monomodalStopPlace:412743","name":"Saint-Denis","disruptionIds":["6bd130e6-10c7-11f0-8f48-0a58a9feac02","6c9372ea-1f55-11f0-9e35-0a58a9feac02","b3d3d1c0-18ef-11f0-8f48-0a58a9feac02","caf1941c-23b9-11f0-b11a-0a58a9feac02","fdcf8210-18ef-11f0-8f48-0a58a9feac02"]},{"type":"stop_point","id":"stop_point:IDFM:monomodalStopPlace:43251","name":"Garges - Sarcelles","disruptionIds":["6bd130e6-10c7-11f0-8f48-0a58a9feac02","6c9372ea-1f55-11f0-9e35-0a58a9feac02","b3d3d1c0-18ef-11f0-8f48-0a58a9feac02","caf1941c-23b9-11f0-b11a-0a58a9feac02","fdcf8210-18ef-11f0-8f48-0a58a9feac02"]},{"type":"stop_point","id":"stop_point:IDFM:monomodalStopPlace:43179","name":"Pierrefitte - Stains","disruptionIds":["6bd130e6-10c7-11f0-8f48-0a58a9feac02","6c9372ea-1f55-11f0-9e35-0a58a9feac02","b3d3d1c0-18ef-11f0-8f48-0a58a9feac02","caf1941c-23b9-11f0-b11a-0a58a9feac02","fdcf8210-18ef-11f0-8f48-0a58a9feac02"]},{"type":"stop_point","id":"stop_point:IDFM:monomodalStopPlace:43222","name":"Villiers-le-Bel - Gonesse - Arnouville","disruptionIds":["6bd130e6-10c7-11f0-8f48-0a58a9feac02","6c9372ea-1f55-11f0-9e35-0a58a9feac02","b3d3d1c0-18ef-11f0-8f48-0a58a9feac02","caf1941c-23b9-11f0-b11a-0a58a9feac02","fdcf8210-18ef-11f0-8f48-0a58a9feac02"]},{"type":"stop_point","id":"stop_point:IDFM:monomodalStopPlace:462394","name":"Gare du Nord","disruptionIds":["6bd130e6-10c7-11f0-8f48-0a58a9feac02","6c9372ea-1f55-11f0-9e35-0a58a9feac02","b3d3d1c0-18ef-11f0-8f48-0a58a9feac02","caf1941c-23b9-11f0-b11a-0a58a9feac02","fdcf8210-18ef-11f0-8f48-0a58a9feac02"]},{"type":"stop_point","id":"stop_point:IDFM:monomodalStopPlace:46304","name":"Villeneuve Triage","disruptionIds":["6bd130e6-10c7-11f0-8f48-0a58a9feac02","6c9372ea-1f55-11f0-9e35-0a58a9feac02","b3d3d1c0-18ef-11f0-8f48-0a58a9feac02","caf1941c-23b9-11f0-b11a-0a58a9feac02","fdcf8210-18ef-11f0-8f48-0a58a9feac02"]},{"type":"stop_point","id":"stop_point:IDFM:monomodalStopPlace:45102","name":"Châtelet les Halles","disruptionIds":["6bd130e6-10c7-11f0-8f48-0a58a9feac02","6c9372ea-1f55-11f0-9e35-0a58a9feac02","b3d3d1c0-18ef-11f0-8f48-0a58a9feac02","caf1941c-23b9-11f0-b11a-0a58a9feac02","fdcf8210-18ef-11f0-8f48-0a58a9feac02"]},{"type":"stop_point","id":"stop_point:IDFM:monomodalStopPlace:47909","name":"Melun","disruptionIds":["95c082d4-24b9-11f0-9be1-0a58a9feac02","97825f10-24ba-11f0-a1ce-0a58a9feac02"]},{"type":"stop_point","id":"stop_point:IDFM:monomodalStopPlace:47876","name":"Goussainville","disruptionIds":["6bd130e6-10c7-11f0-8f48-0a58a9feac02","6c9372ea-1f55-11f0-9e35-0a58a9feac02","b3d3d1c0-18ef-11f0-8f48-0a58a9feac02","caf1941c-23b9-11f0-b11a-0a58a9feac02","fdcf8210-18ef-11f0-8f48-0a58a9feac02"]},{"type":"stop_point","id":"stop_point:IDFM:monomodalStopPlace:47669","name":"Lieusaint - Moissy","disruptionIds":["95c082d4-24b9-11f0-9be1-0a58a9feac02","97825f10-24ba-11f0-a1ce-0a58a9feac02"]},{"type":"stop_point","id":"stop_point:IDFM:monomodalStopPlace:42516","name":"Cesson","disruptionIds":["95c082d4-24b9-11f0-9be1-0a58a9feac02","97825f10-24ba-11f0-a1ce-0a58a9feac02"]},{"type":"stop_point","id":"stop_point:IDFM:monomodalStopPlace:45771","name":"Combs-la-Ville - Quincy","disruptionIds":["6bd130e6-10c7-11f0-8f48-0a58a9feac02","6c9372ea-1f55-11f0-9e35-0a58a9feac02","95c082d4-24b9-11f0-9be1-0a58a9feac02","97825f10-24ba-11f0-a1ce-0a58a9feac02","b3d3d1c0-18ef-11f0-8f48-0a58a9feac02","caf1941c-23b9-11f0-b11a-0a58a9feac02","fdcf8210-18ef-11f0-8f48-0a58a9feac02"]},{"type":"stop_point","id":"stop_point:IDFM:monomodalStopPlace:58873","name":"Brunoy","disruptionIds":["6bd130e6-10c7-11f0-8f48-0a58a9feac02","6c9372ea-1f55-11f0-9e35-0a58a9feac02","b3d3d1c0-18ef-11f0-8f48-0a58a9feac02","caf1941c-23b9-11f0-b11a-0a58a9feac02","fdcf8210-18ef-11f0-8f48-0a58a9feac02"]},{"type":"stop_point","id":"stop_point:IDFM:monomodalStopPlace:47924","name":"Boussy-Saint-Antoine","disruptionIds":["6bd130e6-10c7-11f0-8f48-0a58a9feac02","6c9372ea-1f55-11f0-9e35-0a58a9feac02","b3d3d1c0-18ef-11f0-8f48-0a58a9feac02","caf1941c-23b9-11f0-b11a-0a58a9feac02","fdcf8210-18ef-11f0-8f48-0a58a9feac02"]},{"type":"stop_point","id":"stop_point:IDFM:monomodalStopPlace:43226","name":"Yerres","disruptionIds":["6bd130e6-10c7-11f0-8f48-0a58a9feac02","6c9372ea-1f55-11f0-9e35-0a58a9feac02","b3d3d1c0-18ef-11f0-8f48-0a58a9feac02","caf1941c-23b9-11f0-b11a-0a58a9feac02","fdcf8210-18ef-11f0-8f48-0a58a9feac02"]},{"type":"stop_point","id":"stop_point:IDFM:monomodalStopPlace:47684","name":"Montgeron - Crosne","disruptionIds":["6bd130e6-10c7-11f0-8f48-0a58a9feac02","6c9372ea-1f55-11f0-9e35-0a58a9feac02","b3d3d1c0-18ef-11f0-8f48-0a58a9feac02","caf1941c-23b9-11f0-b11a-0a58a9feac02","fdcf8210-18ef-11f0-8f48-0a58a9feac02"]},{"type":"stop_point","id":"stop_point:IDFM:monomodalStopPlace:45784","name":"Le Mée","disruptionIds":["95c082d4-24b9-11f0-9be1-0a58a9feac02","97825f10-24ba-11f0-a1ce-0a58a9feac02"]},{"type":"stop_point","id":"stop_point:IDFM:monomodalStopPlace:47665","name":"Savigny-le-Temple - Nandy","disruptionIds":["95c082d4-24b9-11f0-9be1-0a58a9feac02","97825f10-24ba-11f0-a1ce-0a58a9feac02"]},{"type":"stop_point","id":"stop_point:IDFM:monomodalStopPlace:45850","name":"Le Bras de Fer","disruptionIds":["7ce66e0e-271b-11f0-ab49-0a58a9feac02"]},{"type":"stop_point","id":"stop_point:IDFM:monomodalStopPlace:48489","name":"Orangis Bois de l'Épine","disruptionIds":["7ce66e0e-271b-11f0-ab49-0a58a9feac02"]},{"type":"stop_point","id":"stop_point:IDFM:monomodalStopPlace:47906","name":"Évry - Courcouronnes","disruptionIds":["7ce66e0e-271b-11f0-ab49-0a58a9feac02"]},{"type":"stop_point","id":"stop_point:IDFM:monomodalStopPlace:43132","name":"Grigny Centre","disruptionIds":["7ce66e0e-271b-11f0-ab49-0a58a9feac02"]}]},{"id":"line:IDFM:C01729","name":"E","shortName":"E","mode":"RapidTransit","networkId":"network:IDFM:71","impactedObjects":[]},{"id":"line:IDFM:C01843","name":"T4","shortName":"T4","mode":"Tramway","networkId":"network:IDFM:Operator_1042","impactedObjects":[{"type":"line","id":"line:IDFM:C01843","name":"T4","disruptionIds":["1d3edd9a-270e-11f0-8e2e-0a58a9feac02"]},{"type":"stop_point","id":"stop_point:IDFM:477286","name":"Clichy-sous-Bois - Mairie","disruptionIds":["1d3edd9a-270e-11f0-8e2e-0a58a9feac02"]},{"type":"stop_point","id":"stop_point:IDFM:478652","name":"Notre-Dame-des-Anges","disruptionIds":["1d3edd9a-270e-11f0-8e2e-0a58a9feac02"]},{"type":"stop_point","id":"stop_point:IDFM:478664","name":"Clichy - Montfermeil","disruptionIds":["1d3edd9a-270e-11f0-8e2e-0a58a9feac02"]},{"type":"stop_point","id":"stop_point:IDFM:478659","name":"Romain Rolland","disruptionIds":["1d3edd9a-270e-11f0-8e2e-0a58a9feac02"]},{"type":"stop_point","id":"stop_point:IDFM:478654","name":"Maurice Audin","disruptionIds":["1d3edd9a-270e-11f0-8e2e-0a58a9feac02"]},{"type":"stop_point","id":"stop_point:IDFM:478650","name":"République - Marx Dormoy","disruptionIds":["1d3edd9a-270e-11f0-8e2e-0a58a9feac02"]},{"type":"stop_point","id":"stop_point:IDFM:478658","name":"Léon Blum","disruptionIds":["1d3edd9a-270e-11f0-8e2e-0a58a9feac02"]},{"type":"stop_point","id":"stop_point:IDFM:478656","name":"Hôpital de Montfermeil","disruptionIds":["1d3edd9a-270e-11f0-8e2e-0a58a9feac02"]},{"type":"stop_point","id":"stop_point:IDFM:478646","name":"Arboretum","disruptionIds":["1d3edd9a-270e-11f0-8e2e-0a58a9feac02"]},{"type":"stop_point","id":"stop_point:IDFM:478651","name":"Arboretum","disruptionIds":["1d3edd9a-270e-11f0-8e2e-0a58a9feac02"]},{"type":"stop_point","id":"stop_point:IDFM:478649","name":"Notre-Dame-des-Anges","disruptionIds":["1d3edd9a-270e-11f0-8e2e-0a58a9feac02"]},{"type":"stop_point","id":"stop_point:IDFM:478661","name":"Clichy - Montfermeil","disruptionIds":["1d3edd9a-270e-11f0-8e2e-0a58a9feac02"]},{"type":"stop_point","id":"stop_point:IDFM:478657","name":"Maurice Audin","disruptionIds":["1d3edd9a-270e-11f0-8e2e-0a58a9feac02"]},{"type":"stop_point","id":"stop_point:IDFM:478663","name":"Clichy-sous-Bois - Mairie","disruptionIds":["1d3edd9a-270e-11f0-8e2e-0a58a9feac02"]},{"type":"stop_point","id":"stop_point:IDFM:478655","name":"Romain Rolland","disruptionIds":["1d3edd9a-270e-11f0-8e2e-0a58a9feac02"]},{"type":"stop_point","id":"stop_point:IDFM:478662","name":"République - Marx Dormoy","disruptionIds":["1d3edd9a-270e-11f0-8e2e-0a58a9feac02"]},{"type":"stop_point","id":"stop_point:IDFM:478653","name":"Léon Blum","disruptionIds":["1d3edd9a-270e-11f0-8e2e-0a58a9feac02"]}]},{"id":"line:IDFM:C01999","name":"T11","shortName":"T11","mode":"Tramway","networkId":"network:IDFM:Operator_1042","impactedObjects":[]},{"id":"line:IDFM:C01737","name":"H","shortName":"H","mode":"LocalTrain","networkId":"network:IDFM:1046","impactedObjects":[]},{"id":"line:IDFM:C01739","name":"J","shortName":"J","mode":"LocalTrain","networkId":"network:IDFM:1046","impactedObjects":[{"type":"line","id":"line:IDFM:C01739","name":"J","disruptionIds":["6a80bafc-1f6f-11f0-ab2b-0a58a9feac02","c3b37bc8-2596-11f0-8217-0a58a9feac02","74cfb94c-271a-11f0-8e2e-0a58a9feac02","74e90f6e-271a-11f0-8e2e-0a58a9feac02"]},{"type":"stop_point","id":"stop_point:IDFM:monomodalStopPlace:43069","name":"Asnières-sur-Seine","disruptionIds":["74cfb94c-271a-11f0-8e2e-0a58a9feac02"]},{"type":"stop_point","id":"stop_point:IDFM:monomodalStopPlace:51238","name":"Bois-Colombes","disruptionIds":["74cfb94c-271a-11f0-8e2e-0a58a9feac02"]},{"type":"stop_point","id":"stop_point:IDFM:monomodalStopPlace:43236","name":"Le Stade","disruptionIds":["6a80bafc-1f6f-11f0-ab2b-0a58a9feac02","74cfb94c-271a-11f0-8e2e-0a58a9feac02"]},{"type":"stop_point","id":"stop_point:IDFM:monomodalStopPlace:43112","name":"Clichy - Levallois","disruptionIds":["74cfb94c-271a-11f0-8e2e-0a58a9feac02"]},{"type":"stop_point","id":"stop_point:IDFM:monomodalStopPlace:47875","name":"Argenteuil","disruptionIds":["6a80bafc-1f6f-11f0-ab2b-0a58a9feac02","74cfb94c-271a-11f0-8e2e-0a58a9feac02"]},{"type":"stop_point","id":"stop_point:IDFM:monomodalStopPlace:58566","name":"Gare Saint-Lazare","disruptionIds":["74cfb94c-271a-11f0-8e2e-0a58a9feac02"]},{"type":"stop_point","id":"stop_point:IDFM:monomodalStopPlace:43113","name":"Colombes","disruptionIds":["74cfb94c-271a-11f0-8e2e-0a58a9feac02"]},{"type":"stop_point","id":"stop_point:IDFM:monomodalStopPlace:45493","name":"Pont Cardinet","disruptionIds":["74cfb94c-271a-11f0-8e2e-0a58a9feac02"]},{"type":"stop_point","id":"stop_point:IDFM:monomodalStopPlace:43212","name":"Val d'Argenteuil","disruptionIds":["6a80bafc-1f6f-11f0-ab2b-0a58a9feac02"]},{"type":"stop_point","id":"stop_point:IDFM:monomodalStopPlace:47898","name":"Ermont - Eaubonne","disruptionIds":["74cfb94c-271a-11f0-8e2e-0a58a9feac02"]},{"type":"stop_point","id":"stop_point:IDFM:monomodalStopPlace:43189","name":"Sannois","disruptionIds":["6a80bafc-1f6f-11f0-ab2b-0a58a9feac02","74cfb94c-271a-11f0-8e2e-0a58a9feac02"]}]},{"id":"line:IDFM:C01738","name":"K","shortName":"K","mode":"LocalTrain","networkId":"network:IDFM:1046","impactedObjects":[]},{"id":"line:IDFM:C01740","name":"L","shortName":"L","mode":"LocalTrain","networkId":"network:IDFM:1046","impactedObjects":[]},{"id":"line:IDFM:C01736","name":"N","shortName":"N","mode":"LocalTrain","networkId":"network:IDFM:1046","impactedObjects":[]},{"id":"line:IDFM:C01730","name":"P","shortName":"P","mode":"LocalTrain","networkId":"network:IDFM:1046","impactedObjects":[{"type":"line","id":"line:IDFM:C01730","name":"P","disruptionIds":["769e6002-0591-11f0-9201-0a58a9feac02"]}]},{"id":"line:IDFM:C01731","name":"R","shortName":"R","mode":"LocalTrain","networkId":"network:IDFM:1046","impactedObjects":[{"type":"line","id":"line:IDFM:C01731","name":"R","disruptionIds":["cfe27566-2717-11f0-976f-0a58a9feac02","cc09385c-2718-11f0-ab49-0a58a9feac02"]}]},{"id":"line:IDFM:C02529","name":"T12","shortName":"T12","mode":"Tramway","networkId":"network:IDFM:1046","impactedObjects":[{"type":"line","id":"line:IDFM:C02529","name":"T12","disruptionIds":["3e06b4aa-271b-11f0-8e2e-0a58a9feac02"]}]},{"id":"line:IDFM:C01741","name":"U","shortName":"U","mode":"LocalTrain","networkId":"network:IDFM:1046","impactedObjects":[]}],"lastUpdatedDate":"2025-05-02T06:09:15.284Z"}